recutils/__init__.py
recutils/parser.py
recutils/recdel.py
recutils/recfix.py
recutils/recinf.py
recutils/recins.py
recutils/recsel.py
recutils/recset.py
recutils/sex.py
python_recutils-0.2.0.dist-info/WHEEL
python_recutils-0.2.0.dist-info/METADATA
python_recutils-0.2.0.dist-info/RECORD
