Metadata-Version: 2.4
Name: python-recutils
Version: 0.2.0
Summary: A python implementation of recutils
Keywords: recutils,rec,parser,database,text-database
Author: Harry Khanna
Author-email: Harry Khanna <harry@khanna.law>
License-Expression: MIT
Classifier: Development Status :: 4 - Beta
Classifier: Intended Audience :: Developers
Classifier: License :: OSI Approved :: MIT License
Classifier: Operating System :: OS Independent
Classifier: Programming Language :: Python :: 3
Classifier: Programming Language :: Python :: 3.12
Classifier: Programming Language :: Python :: 3.13
Classifier: Topic :: Database
Classifier: Topic :: Text Processing
Classifier: Typing :: Typed
Requires-Python: >=3.12
Project-URL: Homepage, https://github.com/hkhanna/python-recutils
